fapp/__init__.py
fapp/analysis.py
fapp/element.py
fapp/node.py
fapp/plotter.py
fapp-1.0.1.dist-info/METADATA
fapp-1.0.1.dist-info/WHEEL
fapp-1.0.1.dist-info/licenses/LICENSE
fapp-1.0.1.dist-info/RECORD
