Metadata-Version: 2.4
Name: fapp
Version: 1.0.1
Summary: fapp (frame analysis program in python) is a simple, easy-to-use implementation of the direct stiffness method.
Project-URL: Homepage, https://github.com/wcfrobert/fapp
Project-URL: Bug Tracker, https://github.com/wcfrobert/fapp/issues
Author-email: wcfrobert <temprobertdev@gmail.com>
License-File: LICENSE
Keywords: FEA,FEM,direct stiffness method,finite element,matrix analysis of structures,structural engineering
Classifier: License :: OSI Approved :: MIT License
Classifier: Operating System :: OS Independent
Classifier: Programming Language :: Python :: 3
Requires-Python: >=3.7
Requires-Dist: numpy>=1.24
Requires-Dist: plotly>=5.13
Requires-Dist: scipy>=1.10
